{
  "角色熟练度：英雄": "",
  "角色熟练度：传说": "",
  "命运的抉择：数学期望": "",
  "命运的抉择：黄字+10%": "",
  "命运的抉择：暴伤+10%": "",
  "命运的抉择：终伤+10%": "",
  "命运的抉择：三攻+10%": "",
  "命运的抉择：技攻+10%": "",
  "骰子：数学期望": "",
  "骰子：1点": "",
  "骰子：2点": "",
  "骰子：3点": "",
  "骰子：4点": "",
  "骰子：5点": "",
  "骰子：6点": "",
  "悲剧的残骸：数学期望": "",
  "悲剧的残骸：HP高于70%": "",
  "悲剧的残骸：HP70-30%": "",
  "悲剧的残骸：HP低于30%": "",
  "先知者预言：数学期望": "",
  "先知者预言：属白+5%": "",
  "先知者预言：技攻+10%": "",
  "先知者预言：技攻+15%": "",
  "贫瘠沙漠的遗产：无": "",
  "贫瘠沙漠的遗产：霸体": "",
  "贫瘠沙漠的遗产：无伤": "",
  "幸运三角：数学期望": "",
  "幸运三角：7效果": "",
  "幸运三角：77效果": "",
  "幸运三角：777效果": "",
  "擎天战甲：过充电状态": "",
  "擎天战甲：过负荷状态": "",
  "持续伤害适用：": "",
  "军神的隐秘遗产：120%以上": "",
  "军神的隐秘遗产：120-100%": "",
  "军神的隐秘遗产：100-80%": "",
  "军神的隐秘遗产：80-60%": "",
  "军神的隐秘遗产：60-40%": "",
  "军神的隐秘遗产：40%以下": "",
  "太极天帝剑：阳": "",
  "太极天帝剑：阴": "",
  "百变怪": "",
  "仅在极速模式和套装模式下生效": "",
  "计算模式：极速模式": "",
  "计算模式：套装模式": "",
  "计算模式：单件模式": "",
  "极速模式：533和3332(散搭) (不含智慧产物)": "",
  "套装模式：533、3332(散搭)和3233(双防具) (不含智慧产物)": "",
  "单件模式：所有组合 (不含百变怪)": "",
  "站街力智": "",
  "站街三攻": "",
  "站街属强": "",
  "一键修正面板细节": "",
  "宠物装备择优": "",
  "7%黄字,8%力智,8%白字,8%三攻取最高值": "",
  "5%黄字，5%暴伤，5%三攻取最高值": "",
  "禁用自动存档": "",
  "神话排名模式": "",
  "仅显示有神话的组合，且每件神话装备只会出现一次": "",
  "亿为单位显示": "",
  "全局重置": "",
  "进程:": "",
  "改造≤{}件": "",
  "不计智慧产物武器以及轮回SS": "",
  "攻击属性:全": "",
  "攻击属性:火": "",
  "攻击属性:冰": "",
  "攻击属性:光": "",
  "攻击属性:暗": "",
  "填写": "",
  "契约满级": "",
  "等级调整": "",
  "TP等级": "",
  "释放次数": "",
  "宠物次数": "",
  "所在等级：": "",
  "等级上限：": "",
  "TP成长：": "",
  "TP上限：": "",
  "最高值参考：": "",
  "符文": "",
  "选择:": "",
  "护石": "",
  "魔界": "",
  "圣痕": "",
  "屏蔽三觉": "",
  "奶量buff力智": "",
  "奶量buff三攻": "",
  "攻击目标：": "",
  "时间输入：": "",
  "开始计算": "",
  "选项": "",
  "无": "",
  "技能": "",
  "增伤词条选择": "",
  "力智": "",
  "三攻": "",
  "黄字": "",
  "白字": "",
  "属白": "",
  "暴伤": "",
  "终伤": "",
  "技攻": "",
  "头部": "",
  "帽子": "",
  "脸部": "",
  "胸部": "",
  "上衣": "",
  "腰带": "",
  "下装": "",
  "鞋": "",
  "高级": "",
  "节日": "",
  "稀有": "",
  "神器": "",
  "高级套装": "",
  "节日套装": "",
  "稀有套装": "",
  "神器套装": "",
  "单件选择": "",
  "锁定": "",
  "武器": "",
  "力量": "",
  "智力": "",
  "物攻": "",
  "魔攻": "",
  "独立": "",
  "属强": "",
  "神话部位：无": "",
  "神话部位：上衣": "",
  "神话部位：手镯": "",
  "神话部位：耳环": "",
  "辟邪玉提升率(理论值仅供参考)": "",
  "查看详情": "",
  "设为基准": "",
  "清空基准": "",
  "数值对比": "",
  "凝固汽油弹": ""
}
