{
  "/carry/data/title": 0,
  "/carry/data/pet": 0,
  "/carry/data/compute_mode": 1,
  "/carry/data/ditto_checked": false,
  "/carry/data/pet_equip_adaptive": false,
  "/carry/data/aura_adaptive": false,
  "/carry/data/myth_top_checked": false,
  "/carry/data/damage_unit": false,
  "/carry/data/thread_count": 1,
  "/carry/data/attack_elemental": 0,
  "/carry/data/remodel_limit": 2,
  "/carry/data/equip_checked": [
    1, 1, 1, 1, 1, 0, 0, 0, 0, 0, 0, 0, 0, 0, 0, 0, 0, 0, 0, 0, 0, 0, 0, 0, 0,
    0, 0, 0, 0, 0, 0, 0, 0, 0, 0, 0, 0, 1, 1, 1, 1, 1, 0, 0, 0, 0, 0, 0, 0, 0,
    0, 0, 0, 0, 0, 0, 0, 0, 0, 0, 0, 0, 0, 0, 0, 0, 0, 0, 0, 0, 0, 0, 0, 0, 0,
    0, 0, 1, 0, 0, 0, 0, 0, 0, 0, 0, 0, 0, 0, 0, 0, 0, 0, 0, 0, 0, 1, 0, 0, 0,
    0, 0, 0, 0, 0, 0, 0, 0, 0, 0, 0, 0, 0, 0, 0, 1, 0, 0, 0, 0, 0, 0, 0, 0, 0,
    0, 0, 0, 0, 0, 0, 0, 0, 0, 1, 0, 0, 0, 0, 0, 0, 0, 0, 0, 0, 0, 0, 0, 0, 1,
    0, 0, 0, 0, 0, 0, 0, 0, 0, 0, 0, 0, 0, 0, 0, 0, 0, 0, 1, 0, 0, 0, 0, 0, 0,
    0, 0, 0, 0, 0, 0, 0, 1, 0, 0, 0, 0, 0, 0, 0, 1, 0, 0, 0, 0, 0, 0, 0, 1, 0,
    0, 0, 0, 0, 0, 0, 1, 0, 0, 0, 0, 0, 1, 0, 0, 0, 0, 0, 0, 0, 1, 0, 0, 0, 0,
    0, 0, 0, 1, 0, 0, 0, 0, 0, 0, 0, 1, 0, 0, 0, 0, 0, 0, 0, 0, 0, 0, 0, 0, 0,
    0, 0, 0, 0, 0, 0, 0, 0, 0, 0, 0, 0, 0, 0, 0, 0, 0, 0, 0, 0, 0, 0, 0, 0, 0,
    0, 0, 0, 0, 0, 0, 0, 0, 0, 0, 0, 0, 0, 0, 0, 0, 0, 0, 0, 0, 0, 0, 0, 0, 0,
    0, 0, 0, 0, 0, 0, 0, 0, 0, 0, 0, 0, 0, 0, 0, 0, 0, 0, 0, 0, 0, 0, 0, 0, 0,
    0, 0, 0, 0, 0, 0, 0, 0, 0, 0, 0, 0, 0, 0, 0, 0, 0, 0, 0, 0, 0, 0, 0, 0, 0,
    0, 0, 0, 0, 0, 0, 0, 0, 0, 0, 0, 0, 0, 0, 0, 0, 0, 0, 0, 0, 0, 0, 0, 0, 0,
    0, 0, 0, 0, 0, 0, 0, 0, 0, 0, 0, 0, 0, 0, 0, 0, 0, 0, 0, 0, 0, 0, 0, 0, 0,
    0, 0, 0, 0, 0, 0, 0, 0, 0, 0, 0, 0, 0, 0, 0, 0, 0, 0, 0, 0, 0, 0, 0, 0, 0,
    0, 0, 0, 0, 0, 0, 0, 0, 0, 0, 0, 0, 0, 0, 0, 0, 0, 0, 0, 0, 0, 0, 0, 0, 0,
    0, 0, 0, 0, 0, 0, 0, 0, 0, 0, 0, 0, 0, 0, 0, 0, 0, 0, 0, 0, 0, 0, 0, 0, 0,
    0, 0, 0, 0, 0, 0, 0, 0, 0, 0, 0, 0, 0, 0, 0, 0, 0, 0, 0, 0, 0, 0, 0, 0, 0,
    0, 0, 0, 0, 0, 0, 0, 0, 0, 0, 0, 0, 0, 0, 0, 0, 0, 0, 0, 0, 0, 0, 0, 0, 0,
    0, 0, 0, 0, 0, 0, 0, 0, 0, 0
  ],
  "/carry/data/equip_forges": [
    1, 1, 1, 1, 1, 1, 1, 1, 0, 1, 1, 0, 10, 10, 10, 10, 10, 10, 10, 10, 12, 10,
    10, 12, 5, 5, 5, 5, 5, 5, 5, 5, 5, 5, 5, 5, 8, 0
  ],
  "/carry/data/equip_conditions": [0, 6, 0, 0, 0, 0, 1, 0, 0, 0, 0, 0],
  "/carry/data/buff_input": "82.0",
  "/carry/data/time_input": 3,
  "/carry/data/awakening_binding": 1,
  "/carry/data/talismans": [6, 7, 1],
  "/carry/data/talisman_types": [0, 0, 1],
  "/carry/data/runes_skills": [11, 11, 11, 11, 11, 11, 11, 11, 11],
  "/carry/data/runes_effects": [15, 14, 13, 15, 14, 13, 15, 14, 13],
  "/carry/data/consumables": [
    true,
    true,
    true,
    true,
    true,
    true,
    true,
    false,
    false,
    false,
    false,
    false,
    false,
    false,
    false,
    false,
    false
  ],
  "/carry/data/skill": {
    "基础精通": {
      "level": 100,
      "tp": 0,
      "count": "0",
      "pet": "0"
    },
    "里鬼剑术": {
      "level": 1,
      "tp": 0,
      "count": "0",
      "pet": "0"
    },
    "武器奥义": {
      "level": 20,
      "tp": 0,
      "count": "0",
      "pet": "0"
    },
    "光剑掌握": {
      "level": 10,
      "tp": 0,
      "count": "0",
      "pet": "0"
    },
    "流心狂": {
      "level": 10,
      "tp": 0,
      "count": "0",
      "pet": "0"
    },
    "无我剑气": {
      "level": 5,
      "tp": 0,
      "count": "0",
      "pet": "0"
    },
    "流心刺": {
      "level": 17,
      "tp": 5,
      "count": "3",
      "pet": "0"
    },
    "流心跃": {
      "level": 41,
      "tp": 5,
      "count": "3",
      "pet": "1"
    },
    "流心升": {
      "level": 38,
      "tp": 5,
      "count": "3",
      "pet": "1"
    },
    "破军升龙击": {
      "level": 38,
      "tp": 0,
      "count": "0",
      "pet": "0"
    },
    "拔刀斩": {
      "level": 36,
      "tp": 5,
      "count": "/CD",
      "pet": "1"
    },
    "破军斩龙击": {
      "level": 33,
      "tp": 0,
      "count": "0",
      "pet": "0"
    },
    "猛龙断空斩": {
      "level": 33,
      "tp": 5,
      "count": "2",
      "pet": "0"
    },
    "幻影剑舞": {
      "level": 31,
      "tp": 5,
      "count": "1",
      "pet": "1"
    },
    "极鬼剑术暴风式": {
      "level": 0,
      "tp": 0,
      "count": "1",
      "pet": "1"
    },
    "极鬼剑术斩铁式": {
      "level": 20,
      "tp": 0,
      "count": "0",
      "pet": "0"
    },
    "极鬼剑术斩钢式": {
      "level": 1,
      "tp": 0,
      "count": "0",
      "pet": "0"
    },
    "极神剑术流星落": {
      "level": 23,
      "tp": 0,
      "count": "0",
      "pet": "0"
    },
    "破空拔刀斩": {
      "level": 18,
      "tp": 5,
      "count": "1",
      "pet": "1"
    },
    "极神剑术破空斩": {
      "level": 16,
      "tp": 0,
      "count": "/CD",
      "pet": "1"
    },
    "极神剑术瞬斩": {
      "level": 13,
      "tp": 0,
      "count": "1",
      "pet": "1"
    },
    "万剑归宗(终结)": {
      "level": 0,
      "tp": 0,
      "count": "1",
      "pet": "1"
    },
    "万剑归宗(穿云刺)": {
      "level": 0,
      "tp": 0,
      "count": "/CD",
      "pet": "1"
    },
    "极神剑术无形斩": {
      "level": 6,
      "tp": 0,
      "count": "1",
      "pet": "1"
    },
    "万剑极诣开天斩": {
      "level": 2,
      "tp": 0,
      "count": "1",
      "pet": "1"
    },
    "极神剑术": {
      "level": 11,
      "tp": 0,
      "count": "0",
      "pet": "0"
    },
    "无形剑意": {
      "level": 4,
      "tp": 0,
      "count": "0",
      "pet": "0"
    },
    "短剑精通": {
      "level": 2,
      "tp": 0,
      "count": "0",
      "pet": "0"
    },
    "太刀精通": {
      "level": 2,
      "tp": 0,
      "count": "0",
      "pet": "0"
    },
    "巨剑精通": {
      "level": 2,
      "tp": 0,
      "count": "0",
      "pet": "0"
    },
    "钝器精通": {
      "level": 2,
      "tp": 0,
      "count": "0",
      "pet": "0"
    },
    "光剑精通": {
      "level": 1,
      "tp": 0,
      "count": "0",
      "pet": "0"
    },
    "空中连斩": {
      "level": 1,
      "tp": 0,
      "count": "0",
      "pet": "0"
    },
    "神影手": {
      "level": 1,
      "tp": 0,
      "count": "0",
      "pet": "0"
    }
  },
  "/carry/data/avatar": [3, 3, 3, 3, 3, 3, 3, 3, 3],
  "/carry/data/detail_values": [
    [
      "120",
      "",
      "15",
      "",
      "290",
      "",
      "50",
      "48",
      "3",
      "",
      "",
      "",
      "",
      "",
      "",
      "",
      ""
    ],
    [
      "120",
      "",
      "15",
      "",
      "290",
      "",
      "50",
      "48",
      "3",
      "",
      "",
      "",
      "",
      "",
      "",
      "",
      ""
    ],
    [
      "",
      "",
      "",
      "10",
      "",
      "40",
      "50",
      "30",
      "",
      "",
      "30",
      "",
      "30",
      "40",
      "",
      "",
      ""
    ],
    [
      "",
      "",
      "",
      "10",
      "",
      "40",
      "50",
      "30",
      "",
      "",
      "30",
      "",
      "30",
      "40",
      "",
      "",
      ""
    ],
    [
      "",
      "",
      "",
      "20",
      "",
      "40",
      "50",
      "30",
      "",
      "",
      "30",
      "",
      "30",
      "40",
      "",
      "",
      ""
    ],
    [
      "",
      "",
      "",
      "8",
      "",
      "",
      "10",
      "7",
      "",
      "",
      "",
      "",
      "",
      "20",
      "16",
      "",
      ""
    ],
    [
      "40",
      "40",
      "75",
      "",
      "",
      "",
      "",
      "",
      "",
      "",
      "150",
      "",
      "",
      "",
      "55",
      "",
      "230"
    ],
    [
      "70",
      "70",
      "20",
      "36",
      "36",
      "",
      "",
      "",
      "",
      "",
      "",
      "30",
      "40",
      "",
      "",
      "",
      ""
    ],
    [
      "",
      "",
      "",
      "",
      "",
      "30",
      "30",
      "30",
      "12",
      "30",
      "",
      "15",
      "15",
      "",
      "",
      "6",
      "10"
    ],
    [
      "40",
      "40",
      "30",
      "70",
      "",
      "",
      "30",
      "70",
      "8",
      "8",
      "",
      "",
      "",
      "",
      "",
      "",
      ""
    ],
    [
      "",
      "",
      "",
      "",
      "40",
      "40",
      "",
      "",
      "",
      "",
      "",
      "",
      "",
      "40",
      "40",
      "40",
      ""
    ],
    ["", "", "", "", "", "", "", ""]
  ],
  "/carry/data/detail_options": [
    [-1, -1, -1, -1, -1, -1, -1, 10, -1, -1, 1, 1, -1, -1, -1, -1, 0],
    [-1, -1, 1, 1, 1, -1, -1, -1, 1, -1, -1, -1, 1, 1, -1, -1, -1],
    [-1, -1, 0, 0, 0, -1, -1, -1, 6, 6, -1, -1, 0, 5, -1, -1, 6]
  ],
  "/carry/data/myth_properties": [
    0, 0, 0, 0, 0, 0, 0, 0, 0, 0, 0, 0, 0, 0, 0, 0, 0, 0, 0, 0, 0, 0, 0, 0, 0,
    0, 0, 0, 0, 0, 0, 0, 0, 0, 0, 0, 0, 0, 0, 0, 0, 0, 0, 0, 0, 0, 0, 0, 0, 0,
    0, 0, 0, 0, 0, 0, 0, 0, 0, 0, 0, 0, 0, 0, 0, 0, 0, 0, 0, 0, 0, 0, 0, 0, 0,
    0, 0, 0, 0, 0, 0, 0, 0, 0, 0, 0, 0, 0, 0, 0, 0, 0, 0, 0, 0, 0, 0, 0, 0, 0,
    0, 0, 0, 0, 0, 0, 0, 0, 0, 0, 0, 0, 0, 0, 0, 0, 0, 0, 0, 0, 0, 0, 0, 0, 0,
    0, 0, 0, 0, 0, 0, 0, 0, 0, 0, 0, 0, 0, 0, 0
  ],
  "/carry/data/remodel_upgrade": false,
  "/carry/data/weapon_adaptive_mode": 0,
  "/carry/data/nameless_elemental_value": 3,
  "/carry/data/siroco_weapon": [0, 0, 0, 0, 0],
  "/carry/data/jude_effects": [0, 0, 0, 0],
  "/carry/data/jude_values": [-1, -1, -1, -1],
  "/carry/data/astaroth_options": [0, 0, 0, 0, 0],
  "/carry/data/black_purgatory": [
    [0, 0, 0],
    [0, 0, 0],
    [0, 0, 0],
    [0, 0, 0]
  ],
  "/carry/data/siroco": [0, 0, 0, 0, 0, 0, 0, 0, 0, 0, 0, 0, 0, 0, 0],
  "/carry/data/ozma": [
    0, 0, 0, 0, 0, 0, 0, 0, 0, 0, 0, 0, 0, 0, 0, 0, 0, 0, 0, 0, 0, 0, 0, 0, 0
  ],
  "/carry/data/self_select/equips": [[3, 3, 3, 3, 3, 2, 2, 2, 8, 0, 0, 0]],
  "/carry/data/self_select/column_index": 0,
  "/carry/data/self_select/locked": [
    false,
    false,
    false,
    false,
    false,
    false,
    false,
    false,
    false,
    false,
    false,
    false
  ],
  "/carry/data/character_sets": {
    "流心刺状态": false,
    "流心跃状态": false,
    "太刀刺伤浮动": 0
  },
  "/carry/data/character_set": {
    "流心刺状态": false,
    "流心跃状态": false,
    "太刀刺伤浮动": 0
  },
  "/carry/data/ancient_memory": 10,
  "/carry/data/kazan": 10
}
